tflink/__init__.py
tflink/client.py
tflink/exceptions.py
tflink/models.py
tflink-0.2.1.dist-info/licenses/LICENSE
tflink-0.2.1.dist-info/METADATA
tflink-0.2.1.dist-info/WHEEL
tflink-0.2.1.dist-info/top_level.txt
tflink-0.2.1.dist-info/RECORD
