Metadata-Version: 2.4
Name: tflink
Version: 0.2.1
Summary: A Python client for tmpfile.link file upload service
Author-email: tfLink <pypi@tmpfile.link>
Maintainer-email: tfLink <pypi@tmpfile.link>
License: MIT
Project-URL: Homepage, https://github.com/tflink-tmpfile/tflink
Project-URL: Documentation, https://github.com/tflink-tmpfile/tflink/tree/main/docs
Project-URL: Repository, https://github.com/tflink-tmpfile/tflink.git
Project-URL: Issues, https://github.com/tflink-tmpfile/tflink/issues
Project-URL: Changelog, https://github.com/tflink-tmpfile/tflink/blob/main/CHANGELOG.md
Keywords: tmpfile,file-upload,file-sharing,tmpfile.link
Classifier: Development Status :: 4 - Beta
Classifier: Intended Audience :: Developers
Classifier: License :: OSI Approved :: MIT License
Classifier: Operating System :: OS Independent
Classifier: Programming Language :: Python :: 3
Classifier: Programming Language :: Python :: 3.8
Classifier: Programming Language :: Python :: 3.9
Classifier: Programming Language :: Python :: 3.10
Classifier: Programming Language :: Python :: 3.11
Classifier: Programming Language :: Python :: 3.12
Classifier: Topic :: Internet :: WWW/HTTP
Classifier: Topic :: Software Development :: Libraries :: Python Modules
Requires-Python: >=3.8
License-File: LICENSE
Requires-Dist: requests>=2.25.0
Provides-Extra: dev
Requires-Dist: pytest>=7.0.0; extra == "dev"
Requires-Dist: pytest-cov>=3.0.0; extra == "dev"
Requires-Dist: pytest-mock>=3.10.0; extra == "dev"
Requires-Dist: black>=22.0.0; extra == "dev"
Requires-Dist: flake8>=4.0.0; extra == "dev"
Requires-Dist: mypy>=0.950; extra == "dev"
Requires-Dist: build>=0.10.0; extra == "dev"
Requires-Dist: twine>=4.0.0; extra == "dev"
Dynamic: license-file
